{     "playerName": "SzyRRogi",     "number": 3,     "levelUp": 3,     "units": [         {             "Line": 0,             "Pole": 0,             "Id": 20,             "Name": "Gryf",             "Cost": 5,             "Initiative": 90,             "MaxHealth": 100,             "Health": 100,             "Attack": 30,             "Defense": 15,             "Range": 0,             "AP": 0,             "MagicResist": 0,             "Description": "Zwiększa iniciatywe wszystkim jednostkom w rzedzie o 10",             "UpgradeLevel": 1,             "SpellId": 0         },         {             "Line": 0,             "Pole": 1,             "Id": 49,             "Name": "Arcymag",             "Cost": 8,             "Initiative": 65,             "MaxHealth": 200,             "Health": 200,             "Attack": 20,             "Defense": 8,             "Range": 1,             "AP": 50,             "MagicResist": 15,             "Description": "Dodaje do puli zaklęcia mocy, może równiez uczyć się zaklęć ognia",             "UpgradeLevel": 1,             "SpellId": 8         },         {             "Line": 0,             "Pole": 2,             "Id": 15,             "Name": "Wilk",             "Cost": 4,             "Initiative": 66,             "MaxHealth": 42,             "Health": 42,             "Attack": 21,             "Defense": 5,             "Range": 0,             "AP": 0,             "MagicResist": 0,             "Description": "Wilk otrzymuje 10 ataku za każdedo przyjaznego wilka na planszy",             "UpgradeLevel": 1,             "SpellId": 0         },         {             "Line": 0,             "Pole": 3,             "Id": 15,             "Name": "Wilk",             "Cost": 4,             "Initiative": 66,             "MaxHealth": 42,             "Health": 42,             "Attack": 21,             "Defense": 5,             "Range": 0,             "AP": 0,             "MagicResist": 0,             "Description": "Wilk otrzymuje 10 ataku za każdedo przyjaznego wilka na planszy",             "UpgradeLevel": 1,             "SpellId": 0         },         {             "Line": 0,             "Pole": 4,             "Id": 43,             "Name": "Plac zwierząt",             "Cost": 5,             "Initiative": 20,             "MaxHealth": 40,             "Health": 40,             "Attack": 0,             "Defense": 0,             "Range": 0,             "AP": 0,             "MagicResist": 0,             "Description": "Zwiększ zwierzętom atak oraz zdrowie o 20",             "UpgradeLevel": 1,             "SpellId": 0         },         {             "Line": 1,             "Pole": 0,             "Id": 4,             "Name": "Jaskółka",             "Cost": 6,             "Initiative": 120,             "MaxHealth": 27,             "Health": 27,             "Attack": 27,             "Defense": 5,             "Range": 0,             "AP": 18,             "MagicResist": 0,             "Description": "Zwiększ Moc Zaklęć wszystkich w rzędzie o wartość swojej mocy umiejętności",             "UpgradeLevel": 3,             "SpellId": 0         },         {             "Line": 1,             "Pole": 1,             "Id": 47,             "Name": "Pyromanta",             "Cost": 10,             "Initiative": 60,             "MaxHealth": 84,             "Health": 84,             "Attack": 28,             "Defense": 5,             "Range": 1,             "AP": 35,             "MagicResist": 10,             "Description": "Włada zakleciami ognia",             "UpgradeLevel": 2,             "SpellId": 6         },         {             "Line": 1,             "Pole": 2,             "Id": 1,             "Name": "Adept",             "Cost": 9,             "Initiative": 60,             "MaxHealth": 81,             "Health": 81,             "Attack": 18,             "Defense": 5,             "Range": 1,             "AP": 45,             "MagicResist": 15,             "Description": "Adept podczas ataku, zadaje obrażenia magiczne",             "UpgradeLevel": 1,             "SpellId": 0         },         {             "Line": 1,             "Pole": 3,             "Id": 4,             "Name": "Jaskółka",             "Cost": 2,             "Initiative": 100,             "MaxHealth": 15,             "Health": 15,             "Attack": 15,             "Defense": 5,             "Range": 0,             "AP": 10,             "MagicResist": 0,             "Description": "Zwiększ Moc Zaklęć wszystkich w rzędzie o wartość swojej mocy umiejętności",             "UpgradeLevel": 1,             "SpellId": 0         },         {             "Line": 2,             "Pole": 1,             "Id": 12,             "Name": "Rycerz",             "Cost": 3,             "Initiative": 40,             "MaxHealth": 65,             "Health": 65,             "Attack": 20,             "Defense": 15,             "Range": 0,             "AP": 0,             "MagicResist": 0,             "Description": "Zwiększa obronę o 30 przy atakach z dystansu",             "UpgradeLevel": 1,             "SpellId": 0         },         {             "Line": 2,             "Pole": 2,             "Id": 16,             "Name": "Budowlaniec",             "Cost": 5,             "Initiative": 50,             "MaxHealth": 50,             "Health": 50,             "Attack": 15,             "Defense": 5,             "Range": 0,             "AP": 0,             "MagicResist": 0,             "Description": "Zmniejsza koszt budynków w sklepie o 2",             "UpgradeLevel": 1,             "SpellId": 0         },         {             "Line": 2,             "Pole": 3,             "Id": 14,             "Name": "Wilk",             "Cost": 2,             "Initiative": 60,             "MaxHealth": 30,             "Health": 30,             "Attack": 15,             "Defense": 5,             "Range": 0,             "AP": 0,             "MagicResist": 0,             "Description": "Wilk otrzymuje 5 ataku za każdedo przyjaznego wilka na planszy",             "UpgradeLevel": 1,             "SpellId": 0         },         {             "Line": 2,             "Pole": 5,             "Id": 40,             "Name": "Namiot Rekrutów ",             "Cost": 5,             "Initiative": 20,             "MaxHealth": 30,             "Health": 30,             "Attack": 0,             "Defense": 0,             "Range": 0,             "AP": 0,             "MagicResist": 0,             "Description": "Zapewnia 2 darmowe odświerzenia sklepu na początku rundy",             "UpgradeLevel": 1,             "SpellId": 0         }     ] }